[{"id":"1106063001","district_id":"1106063","name":"MERANDEH PAYA"},{"id":"1106063002","district_id":"1106063","name":"TANJUNG"},{"id":"1106063003","district_id":"1106063","name":"RUSIP"},{"id":"1106063004","district_id":"1106063","name":"PAYA TAMPU"},{"id":"1106063005","district_id":"1106063","name":"KUALA RAWA"},{"id":"1106063006","district_id":"1106063","name":"PANTAN TENGAH"},{"id":"1106063007","district_id":"1106063","name":"PILAR"},{"id":"1106063008","district_id":"1106063","name":"ARUL PERTIK"},{"id":"1106063009","district_id":"1106063","name":"ATU SINGKIH"},{"id":"1106063010","district_id":"1106063","name":"PANTAN BENER"},{"id":"1106063011","district_id":"1106063","name":"KERAWANG"},{"id":"1106063012","district_id":"1106063","name":"PILAR JAYA"},{"id":"1106063013","district_id":"1106063","name":"TIRMI ARA"},{"id":"1106063014","district_id":"1106063","name":"MEKAR MAJU"},{"id":"1106063015","district_id":"1106063","name":"PILAR WIH KIRI"},{"id":"1106063016","district_id":"1106063","name":"LAUT JAYA"}]