[{"id":"1110101001","district_id":"1110101","name":"PARANG SIKUREUNG"},{"id":"1110101002","district_id":"1110101","name":"TANJONG SIRON"},{"id":"1110101003","district_id":"1110101","name":"PALOH RAYA"},{"id":"1110101004","district_id":"1110101","name":"PALOH PEURADI"},{"id":"1110101005","district_id":"1110101","name":"CRUNG KUMBANG"},{"id":"1110101006","district_id":"1110101","name":"PALOH DAMA"},{"id":"1110101007","district_id":"1110101","name":"BUKIT DALAM"},{"id":"1110101008","district_id":"1110101","name":"GLE PUTOH"},{"id":"1110101009","district_id":"1110101","name":"BALE ME"},{"id":"1110101010","district_id":"1110101","name":"KULU"},{"id":"1110101011","district_id":"1110101","name":"BLANG ME"},{"id":"1110101012","district_id":"1110101","name":"BLANG PANJOE"},{"id":"1110101013","district_id":"1110101","name":"LHOK NGA"},{"id":"1110101014","district_id":"1110101","name":"MEUSE"},{"id":"1110101015","district_id":"1110101","name":"BABAH JURONG"},{"id":"1110101016","district_id":"1110101","name":"DAYAH PANJOE"},{"id":"1110101017","district_id":"1110101","name":"IEMBUDEE"},{"id":"1110101018","district_id":"1110101","name":"TINGKEUM BARO"},{"id":"1110101019","district_id":"1110101","name":"PULO REUDEUP"},{"id":"1110101020","district_id":"1110101","name":"TINGKEUM MANYANG"},{"id":"1110101021","district_id":"1110101","name":"ULEE PUSONG"},{"id":"1110101022","district_id":"1110101","name":"PAYA RANGKULUH"},{"id":"1110101023","district_id":"1110101","name":"COT BAROH"},{"id":"1110101024","district_id":"1110101","name":"BABAH SUAK"},{"id":"1110101025","district_id":"1110101","name":"GEULANGGANG RAYEUK"},{"id":"1110101026","district_id":"1110101","name":"GEULANGGANG MEUNJE"},{"id":"1110101027","district_id":"1110101","name":"GEULANGGANG PANAH"},{"id":"1110101028","district_id":"1110101","name":"PULO BLANG"},{"id":"1110101029","district_id":"1110101","name":"PULO SIRON"},{"id":"1110101030","district_id":"1110101","name":"JARUM MAHME"},{"id":"1110101031","district_id":"1110101","name":"DAYAH MESJID"},{"id":"1110101032","district_id":"1110101","name":"UJONG BLANG"},{"id":"1110101033","district_id":"1110101","name":"KEURUMBOK"},{"id":"1110101034","district_id":"1110101","name":"JARUMMAH BAROH"},{"id":"1110101035","district_id":"1110101","name":"COT ARA"},{"id":"1110101036","district_id":"1110101","name":"RANCONG"},{"id":"1110101037","district_id":"1110101","name":"PULO NGA"},{"id":"1110101038","district_id":"1110101","name":"COT ME"},{"id":"1110101039","district_id":"1110101","name":"JAMBO KAJEUNG"},{"id":"1110101040","district_id":"1110101","name":"KULU KUTA"},{"id":"1110101041","district_id":"1110101","name":"PULO AWE"}]