[{"id":"1214033001","district_id":"1214033","name":"HILISIMAETANO"},{"id":"1214033003","district_id":"1214033","name":"BAWOGOSALI"},{"id":"1214033004","district_id":"1214033","name":"HILIFALAWU"},{"id":"1214033006","district_id":"1214033","name":"SOTOO HILISIMAETANO"},{"id":"1214033007","district_id":"1214033","name":"EHO HILISIMAETANO"},{"id":"1214033008","district_id":"1214033","name":"SAMADAYA HILISIMAETANO"},{"id":"1214033009","district_id":"1214033","name":"IDALA JAYA HILISIMAETANO"},{"id":"1214033010","district_id":"1214033","name":"FAOMASI HILISIMAETANO"},{"id":"1214033011","district_id":"1214033","name":"HILIAURIFA HILISIMAETANO"},{"id":"1214033012","district_id":"1214033","name":"NDRASO HILISIMAETANO"},{"id":"1214033013","district_id":"1214033","name":"PEKAN HILISIMAETANO"},{"id":"1214033014","district_id":"1214033","name":"BONIA HILISIMAETANO"},{"id":"1214033015","district_id":"1214033","name":"BAWOSAODANO"},{"id":"1214033016","district_id":"1214033","name":"BOWOHOSI"}]