[{"id":"1219021001","district_id":"1219021","name":"TANJUNG MULIA"},{"id":"1219021002","district_id":"1219021","name":"SUNGAI MENTARAM"},{"id":"1219021003","district_id":"1219021","name":"PEMATANG RAMBAI"},{"id":"1219021004","district_id":"1219021","name":"BAGAN BARU"},{"id":"1219021005","district_id":"1219021","name":"UJUNG KUBU"},{"id":"1219021006","district_id":"1219021","name":"LIMA LARAS"},{"id":"1219021007","district_id":"1219021","name":"SENTANG"},{"id":"1219021008","district_id":"1219021","name":"JATI MULIA"},{"id":"1219021009","district_id":"1219021","name":"TALI AIR PERMAI"},{"id":"1219021010","district_id":"1219021","name":"KAPAL MERAH"},{"id":"1219021011","district_id":"1219021","name":"BANDAR SONO"},{"id":"1219021012","district_id":"1219021","name":"MEKAR LARAS"}]