[{"id":"1219070001","district_id":"1219070","name":"SIDO MULYO"},{"id":"1219070002","district_id":"1219070","name":"AEK NAULI"},{"id":"1219070003","district_id":"1219070","name":"SEI BUAH KERAS"},{"id":"1219070004","district_id":"1219070","name":"SEI RAKYAT"},{"id":"1219070005","district_id":"1219070","name":"TANJUNG SIGONI"},{"id":"1219070006","district_id":"1219070","name":"PEMATANG CENGKRING"},{"id":"1219070007","district_id":"1219070","name":"PAKAM RAYA"},{"id":"1219070008","district_id":"1219070","name":"PAKAM"},{"id":"1219070009","district_id":"1219070","name":"LALANG"},{"id":"1219070010","district_id":"1219070","name":"MEDANG"},{"id":"1219070011","district_id":"1219070","name":"DURIAN"},{"id":"1219070012","district_id":"1219070","name":"NENAS SIAM"},{"id":"1219070013","district_id":"1219070","name":"PANGKALAN DODEK BARU"},{"id":"1219070014","district_id":"1219070","name":"PANGKALAN DODEK"},{"id":"1219070015","district_id":"1219070","name":"SEI RAJA"},{"id":"1219070016","district_id":"1219070","name":"CENGKERING PEKAN"},{"id":"1219070017","district_id":"1219070","name":"PAKAM RAYA SELATAN"},{"id":"1219070018","district_id":"1219070","name":"MANDARSAH"},{"id":"1219070019","district_id":"1219070","name":"MEDANG BARU"},{"id":"1219070020","district_id":"1219070","name":"PEMATANG NIBUNG"},{"id":"1219070021","district_id":"1219070","name":"PAGURAWAN"}]