[{"id":"1501071001","district_id":"1501071","name":"KEMANTAN HILIR"},{"id":"1501071002","district_id":"1501071","name":"KOTO TEBAT"},{"id":"1501071003","district_id":"1501071","name":"PONDOK SUNGAI ABU"},{"id":"1501071004","district_id":"1501071","name":"SUNGAI ABU"},{"id":"1501071005","district_id":"1501071","name":"PUNGUT HILIR"},{"id":"1501071006","district_id":"1501071","name":"PUNGUT TENGAH"},{"id":"1501071007","district_id":"1501071","name":"PUNGUT MUDIK"},{"id":"1501071008","district_id":"1501071","name":"DESA BARU SEI TUTUNG"},{"id":"1501071009","district_id":"1501071","name":"SUNGAI TUTUNG"},{"id":"1501071010","district_id":"1501071","name":"SUNGAI MEDANG"},{"id":"1501071013","district_id":"1501071","name":"AIR HANGAT"},{"id":"1501071014","district_id":"1501071","name":"KEMANTAN TINGGI"},{"id":"1501071015","district_id":"1501071","name":"KEMANTAN AGUNG"},{"id":"1501071016","district_id":"1501071","name":"KEMANTAN KEBALAI"},{"id":"1501071017","district_id":"1501071","name":"KEMANTAN DARAT"},{"id":"1501071018","district_id":"1501071","name":"SUNGAI DERAS"},{"id":"1501071019","district_id":"1501071","name":"SIMPANG EMPAT SUNGAI TUTUNG"},{"id":"1501071020","district_id":"1501071","name":"KEMANTAN MUDIK"},{"id":"1501071021","district_id":"1501071","name":"BARU SUNGAI DERAS"},{"id":"1501071022","district_id":"1501071","name":"AIR PANAS SUNGAI ABU"},{"id":"1501071023","district_id":"1501071","name":"BARU SUNGAI ABU"},{"id":"1501071024","district_id":"1501071","name":"TAMAN JERNIH SUNGAI TUTUNG"},{"id":"1501071025","district_id":"1501071","name":"BARU SUNGAI MEDANG"},{"id":"1501071026","district_id":"1501071","name":"BARU AIR HANGAT"},{"id":"1501071027","district_id":"1501071","name":"KEMANTAN RAYA"}]