[{"id":"1503020001","district_id":"1503020","name":"MERSIP"},{"id":"1503020002","district_id":"1503020","name":"DESA BERKUN"},{"id":"1503020003","district_id":"1503020","name":"LUBUK BEDORONG"},{"id":"1503020004","district_id":"1503020","name":"MERIBUNG"},{"id":"1503020005","district_id":"1503020","name":"NAPAL MELINTANG"},{"id":"1503020007","district_id":"1503020","name":"PANCA KARYA"},{"id":"1503020008","district_id":"1503020","name":"RANGGO"},{"id":"1503020009","district_id":"1503020","name":"TANJUNG RADEN"},{"id":"1503020010","district_id":"1503020","name":"TEMENGGUNG"},{"id":"1503020011","district_id":"1503020","name":"PULAU PANDAN"},{"id":"1503020015","district_id":"1503020","name":"DEMANG"},{"id":"1503020016","district_id":"1503020","name":"MUARA MANSAO"},{"id":"1503020017","district_id":"1503020","name":"MOENTI"},{"id":"1503020018","district_id":"1503020","name":"MUARA LIMUN"},{"id":"1503020019","district_id":"1503020","name":"SUKA DAMAI"},{"id":"1503020020","district_id":"1503020","name":"TEMALANG"}]