[{"id":"1572031001","district_id":"1572031","name":"SUNGAI JERNIH"},{"id":"1572031002","district_id":"1572031","name":"KOTO LEBU"},{"id":"1572031003","district_id":"1572031","name":"KARYA BAKTI"},{"id":"1572031004","district_id":"1572031","name":"LAWANG AGUNG"},{"id":"1572031005","district_id":"1572031","name":"KELURAHAN PONDOK TINGGI"},{"id":"1572031006","district_id":"1572031","name":"PERMANTI"},{"id":"1572031007","district_id":"1572031","name":"PONDOK AGUNG"},{"id":"1572031008","district_id":"1572031","name":"AUR DURI"}]