[{"id":"1601052001","district_id":"1601052","name":"BANDAR JAYA"},{"id":"1601052002","district_id":"1601052","name":"KARANG ENDAH"},{"id":"1601052003","district_id":"1601052","name":"PAJAR BULAN"},{"id":"1601052004","district_id":"1601052","name":"PAGAR DEWA"},{"id":"1601052005","district_id":"1601052","name":"TANJUNG LENGKAYAP"},{"id":"1601052006","district_id":"1601052","name":"BUMI KAWA"},{"id":"1601052007","district_id":"1601052","name":"NEGERI RATU"},{"id":"1601052008","district_id":"1601052","name":"LUBUK DALAM"},{"id":"1601052009","district_id":"1601052","name":"SEGARA KEMBANG"},{"id":"1601052010","district_id":"1601052","name":"SUKARAJA"},{"id":"1601052011","district_id":"1601052","name":"GEDUNG PAKUAN"},{"id":"1601052012","district_id":"1601052","name":"TUALANG"},{"id":"1601052013","district_id":"1601052","name":"SUNDAN"},{"id":"1601052014","district_id":"1601052","name":"TIHANG"},{"id":"1601052015","district_id":"1601052","name":"LUBUK HARA"},{"id":"1601052016","district_id":"1601052","name":"NEGERI AGUNG"},{"id":"1601052017","district_id":"1601052","name":"WAY HELING"},{"id":"1601052018","district_id":"1601052","name":"BUNGA TANJUNG"},{"id":"1601052019","district_id":"1601052","name":"UMPAM"},{"id":"1601052020","district_id":"1601052","name":"TANJUNG AGUNG"},{"id":"1601052021","district_id":"1601052","name":"SIMPANG EMPAT"},{"id":"1601052022","district_id":"1601052","name":"FAJAR JAYA"}]