[{"id":"1806020001","district_id":"1806020","name":"TULUNG BALAK"},{"id":"1806020002","district_id":"1806020","name":"SUKA MULYA"},{"id":"1806020003","district_id":"1806020","name":"GUNUNG KATON"},{"id":"1806020004","district_id":"1806020","name":"KARANG WARINGIN"},{"id":"1806020005","district_id":"1806020","name":"SUKASARI"},{"id":"1806020006","district_id":"1806020","name":"SIDO MULYO"},{"id":"1806020007","district_id":"1806020","name":"TANJUNG BERINGIN"},{"id":"1806020008","district_id":"1806020","name":"MERAMBUNG"},{"id":"1806020009","district_id":"1806020","name":"SINAR JAYA"},{"id":"1806020010","district_id":"1806020","name":"SINDANG AGUNG"},{"id":"1806020011","district_id":"1806020","name":"MEKAR JAYA"},{"id":"1806020012","district_id":"1806020","name":"SRI MENANTI"},{"id":"1806020013","district_id":"1806020","name":"TANJUNG RAJA"},{"id":"1806020014","district_id":"1806020","name":"TANJUNG RIANG"},{"id":"1806020015","district_id":"1806020","name":"KEMALA RAJA"},{"id":"1806020016","district_id":"1806020","name":"ULAK ATA"},{"id":"1806020017","district_id":"1806020","name":"SINDANG MARGA"},{"id":"1806020018","district_id":"1806020","name":"SINAR MULYA"},{"id":"1806020019","district_id":"1806020","name":"PRIANGAN BARU"}]