[{"id":"1810040007","district_id":"1810040","name":"MARGAKAYA"},{"id":"1810040008","district_id":"1810040","name":"WALUYOJATI"},{"id":"1810040009","district_id":"1810040","name":"PAJAR ESUK"},{"id":"1810040011","district_id":"1810040","name":"SIDOHARJO"},{"id":"1810040012","district_id":"1810040","name":"PODOMORO"},{"id":"1810040013","district_id":"1810040","name":"BUMI ARUM"},{"id":"1810040015","district_id":"1810040","name":"PAJAR AGUNG"},{"id":"1810040016","district_id":"1810040","name":"PRINGSEWU UTARA"},{"id":"1810040017","district_id":"1810040","name":"PRINGSEWU SELATAN"},{"id":"1810040018","district_id":"1810040","name":"PRINGSEWU BARAT"},{"id":"1810040019","district_id":"1810040","name":"PRINGSEWU TIMUR"},{"id":"1810040020","district_id":"1810040","name":"REJOSARI"},{"id":"1810040021","district_id":"1810040","name":"BUMI AYU"},{"id":"1810040022","district_id":"1810040","name":"PODOSARI"},{"id":"1810040023","district_id":"1810040","name":"FAJAR AGUNG BARAT"}]