[{"id":"3202060001","district_id":"3202060","name":"SUMBERJAYA"},{"id":"3202060002","district_id":"3202060","name":"BUNIASIH"},{"id":"3202060003","district_id":"3202060","name":"TEGALBULEUD"},{"id":"3202060004","district_id":"3202060","name":"CALINGCING"},{"id":"3202060005","district_id":"3202060","name":"RAMBAY"},{"id":"3202060006","district_id":"3202060","name":"NANGELA"},{"id":"3202060007","district_id":"3202060","name":"BANGBAYANG"},{"id":"3202060008","district_id":"3202060","name":"SIRNAMEKAR"}]