[{"id":"3301110001","district_id":"3301110","name":"BANTARSARI"},{"id":"3301110002","district_id":"3301110","name":"RAWAJAYA"},{"id":"3301110003","district_id":"3301110","name":"BINANGUN"},{"id":"3301110004","district_id":"3301110","name":"BULAKSARI"},{"id":"3301110005","district_id":"3301110","name":"KAMULYAN"},{"id":"3301110006","district_id":"3301110","name":"CIKEDONDONG"},{"id":"3301110007","district_id":"3301110","name":"KEDUNGWADAS"},{"id":"3301110008","district_id":"3301110","name":"CITEMBONG"}]