[{"id":"3312130001","district_id":"3312130","name":"KEPATIHAN"},{"id":"3312130002","district_id":"3312130","name":"KELORAN"},{"id":"3312130003","district_id":"3312130","name":"PARE"},{"id":"3312130004","district_id":"3312130","name":"SINGODUTAN"},{"id":"3312130005","district_id":"3312130","name":"KALIANCAR"},{"id":"3312130006","district_id":"3312130","name":"JENDI"},{"id":"3312130008","district_id":"3312130","name":"JATEN"},{"id":"3312130009","district_id":"3312130","name":"GEMANTAR"},{"id":"3312130010","district_id":"3312130","name":"NAMBANGAN"},{"id":"3312130011","district_id":"3312130","name":"SENDANGIJO"}]