[{"id":"3401060001","district_id":"3401060","name":"DEMANGREJO"},{"id":"3401060002","district_id":"3401060","name":"SRIKAYANGAN"},{"id":"3401060003","district_id":"3401060","name":"TUKSONO"},{"id":"3401060004","district_id":"3401060","name":"SALAMREJO"},{"id":"3401060005","district_id":"3401060","name":"SUKORENO"},{"id":"3401060006","district_id":"3401060","name":"KALIAGUNG"},{"id":"3401060007","district_id":"3401060","name":"SENTOLO"},{"id":"3401060008","district_id":"3401060","name":"BANGUNCIPTO"}]