[{"id":"3526120001","district_id":"3526120","name":"JAMBU"},{"id":"3526120002","district_id":"3526120","name":"LANGKAP"},{"id":"3526120004","district_id":"3526120","name":"BENANGKAH"},{"id":"3526120005","district_id":"3526120","name":"ALAS KEMBANG"},{"id":"3526120006","district_id":"3526120","name":"BINOH"},{"id":"3526120008","district_id":"3526120","name":"PANGOLANGAN"},{"id":"3526120009","district_id":"3526120","name":"SOBIH"},{"id":"3526120010","district_id":"3526120","name":"TONJUNG"},{"id":"3526120011","district_id":"3526120","name":"KAPOR"},{"id":"3526120012","district_id":"3526120","name":"AROK"}]