[{"id":"3571020001","district_id":"3571020","name":"MANISRENGGO"},{"id":"3571020002","district_id":"3571020","name":"REJOMULYO"},{"id":"3571020003","district_id":"3571020","name":"NGRONGGO"},{"id":"3571020004","district_id":"3571020","name":"KALIOMBO"},{"id":"3571020005","district_id":"3571020","name":"KAMPUNG DALEM"},{"id":"3571020006","district_id":"3571020","name":"SETONO PANDE"},{"id":"3571020007","district_id":"3571020","name":"RINGIN ANOM"},{"id":"3571020008","district_id":"3571020","name":"PAKELAN"},{"id":"3571020009","district_id":"3571020","name":"SETONO GEDONG"},{"id":"3571020010","district_id":"3571020","name":"KEMASAN"},{"id":"3571020011","district_id":"3571020","name":"JAGALAN"},{"id":"3571020012","district_id":"3571020","name":"BANJARAN"},{"id":"3571020013","district_id":"3571020","name":"NGADIREJO"},{"id":"3571020014","district_id":"3571020","name":"DANDANGAN"},{"id":"3571020015","district_id":"3571020","name":"BALOWERTI"},{"id":"3571020016","district_id":"3571020","name":"POCANAN"},{"id":"3571020017","district_id":"3571020","name":"SEMAMPIR"}]