[{"id":"3601050001","district_id":"3601050","name":"BANYUASIH"},{"id":"3601050002","district_id":"3601050","name":"KARANGBOLONG"},{"id":"3601050003","district_id":"3601050","name":"KARYABUANA"},{"id":"3601050004","district_id":"3601050","name":"KATUMBIRI"},{"id":"3601050005","district_id":"3601050","name":"WARINGINJAYA"},{"id":"3601050006","district_id":"3601050","name":"SINARJAYA"},{"id":"3601050007","district_id":"3601050","name":"CISEUREUHEUN"},{"id":"3601050009","district_id":"3601050","name":"CIGEULIS"},{"id":"3601050010","district_id":"3601050","name":"TARUMANAGARA"}]