[{"id":"5312031001","district_id":"5312031","name":"BAWARANI"},{"id":"5312031002","district_id":"5312031","name":"WOGOWELA"},{"id":"5312031003","district_id":"5312031","name":"WATUSIPI"},{"id":"5312031004","district_id":"5312031","name":"BOBA"},{"id":"5312031005","district_id":"5312031","name":"BOBA I"},{"id":"5312031006","district_id":"5312031","name":"WERE II"},{"id":"5312031007","district_id":"5312031","name":"WERE III"},{"id":"5312031008","district_id":"5312031","name":"KEZEWEA"},{"id":"5312031009","district_id":"5312031","name":"NIRMALA"},{"id":"5312031010","district_id":"5312031","name":"TAKATUNGA"},{"id":"5312031011","district_id":"5312031","name":"SADHA"},{"id":"5312031012","district_id":"5312031","name":"RADAMASA"}]