[{"id":"7107010001","district_id":"7107010","name":"SANGTOMBOLANG"},{"id":"7107010002","district_id":"7107010","name":"SAMPIRO"},{"id":"7107010003","district_id":"7107010","name":"SANGKUB I"},{"id":"7107010004","district_id":"7107010","name":"SANGKUB II"},{"id":"7107010005","district_id":"7107010","name":"SANGKUB III"},{"id":"7107010006","district_id":"7107010","name":"TOMBOLANGO"},{"id":"7107010007","district_id":"7107010","name":"BUSISINGO"},{"id":"7107010008","district_id":"7107010","name":"PANGKUSA"},{"id":"7107010009","district_id":"7107010","name":"SIDODADI"},{"id":"7107010010","district_id":"7107010","name":"BUSISINGO UTARA"},{"id":"7107010011","district_id":"7107010","name":"SANGKUB IV"},{"id":"7107010012","district_id":"7107010","name":"APENG SEMBEKA"},{"id":"7107010013","district_id":"7107010","name":"SANGKUB TIMUR"},{"id":"7107010014","district_id":"7107010","name":"MONOMPIA"},{"id":"7107010015","district_id":"7107010","name":"SUKA MAKMUR"},{"id":"7107010016","district_id":"7107010","name":"MOKUSATO"}]