[{"id":"7311090001","district_id":"7311090","name":"BALIENG TOA"},{"id":"7311090002","district_id":"7311090","name":"PASAKA"},{"id":"7311090003","district_id":"7311090","name":"BULIE"},{"id":"7311090005","district_id":"7311090","name":"MASSENRENGPULU"},{"id":"7311090006","district_id":"7311090","name":"MABBIRING"},{"id":"7311090007","district_id":"7311090","name":"MALLUSETASI"},{"id":"7311090008","district_id":"7311090","name":"PATTIRO SOMPE"},{"id":"7311090009","district_id":"7311090","name":"PAKKASALO"},{"id":"7311090010","district_id":"7311090","name":"PATTIRO BAJO"},{"id":"7311090011","district_id":"7311090","name":"MAROANGING"},{"id":"7311090012","district_id":"7311090","name":"CINNONG"},{"id":"7311090013","district_id":"7311090","name":"POLEWALI"},{"id":"7311090014","district_id":"7311090","name":"KALIBONG"},{"id":"7311090015","district_id":"7311090","name":"TADANG PALIE"},{"id":"7311090016","district_id":"7311090","name":"AJANG PULU"},{"id":"7311090017","district_id":"7311090","name":"LETTE TANAH"},{"id":"7311090018","district_id":"7311090","name":"PATTIRO RIOLO"},{"id":"7311090019","district_id":"7311090","name":"SUMPANG MINANGAE"},{"id":"7311090020","district_id":"7311090","name":"MANAJENG"}]