[{"id":"7311050001","district_id":"7311050","name":"BICCOING"},{"id":"7311050002","district_id":"7311050","name":"BACU"},{"id":"7311050003","district_id":"7311050","name":"MUARA"},{"id":"7311050005","district_id":"7311050","name":"GARECCING"},{"id":"7311050006","district_id":"7311050","name":"BONEPUTE"},{"id":"7311050008","district_id":"7311050","name":"PADATUO"},{"id":"7311050009","district_id":"7311050","name":"LIBURENG"},{"id":"7311050010","district_id":"7311050","name":"SAMAENRE"},{"id":"7311050011","district_id":"7311050","name":"RAPPA"}]