[{"id":"7325031003","district_id":"7325031","name":"MANUNGGAL"},{"id":"7325031004","district_id":"7325031","name":"ALAM BUANA"},{"id":"7325031005","district_id":"7325031","name":"CENDANA HITAM"},{"id":"7325031006","district_id":"7325031","name":"KERTARAHARJO"},{"id":"7325031007","district_id":"7325031","name":"MARGOMULYO"},{"id":"7325031018","district_id":"7325031","name":"PURWOSARI"},{"id":"7325031019","district_id":"7325031","name":"PATENGKO"},{"id":"7325031020","district_id":"7325031","name":"CENDANA HITAM TIMUR"}]