[{"id":"7326080001","district_id":"7326080","name":"KELURAHAN TAMPO TALLUNGLIPU"},{"id":"7326080002","district_id":"7326080","name":"KELURAHAN TAGARI TALLUNG LIPU"},{"id":"7326080003","district_id":"7326080","name":"KELURAHAN RANTE PAKU TALLUNGLIPU"},{"id":"7326080004","district_id":"7326080","name":"KELURAHAN TALLUNGLIPU MATALLO"},{"id":"7326080005","district_id":"7326080","name":"KELURAHAN TALLUNG LIPU"},{"id":"7326080006","district_id":"7326080","name":"KELURAHAN TANTANAN TALLUNGLIPU"},{"id":"7326080007","district_id":"7326080","name":"LEMBANG BUNTU TALLUNGLIPU"}]