[{"id":"9433030003","district_id":"9433030","name":"KAGO"},{"id":"9433030004","district_id":"9433030","name":"KIMAK"},{"id":"9433030015","district_id":"9433030","name":"WULONI"},{"id":"9433030016","district_id":"9433030","name":"NIPURALOME"},{"id":"9433030017","district_id":"9433030","name":"KIBOGOLOME"},{"id":"9433030018","district_id":"9433030","name":"TAGALOA"},{"id":"9433030019","district_id":"9433030","name":"JENGGERPAGA"},{"id":"9433030020","district_id":"9433030","name":"ILMABET"},{"id":"9433030021","district_id":"9433030","name":"KALEBUT"}]