[{"id":"3308010","regency_id":"3308","name":"SALAMAN"},{"id":"3308020","regency_id":"3308","name":"BOROBUDUR"},{"id":"3308030","regency_id":"3308","name":"NGLUWAR"},{"id":"3308040","regency_id":"3308","name":"SALAM"},{"id":"3308050","regency_id":"3308","name":"SRUMBUNG"},{"id":"3308060","regency_id":"3308","name":"DUKUN"},{"id":"3308070","regency_id":"3308","name":"MUNTILAN"},{"id":"3308080","regency_id":"3308","name":"MUNGKID"},{"id":"3308090","regency_id":"3308","name":"SAWANGAN"},{"id":"3308100","regency_id":"3308","name":"CANDIMULYO"},{"id":"3308110","regency_id":"3308","name":"MERTOYUDAN"},{"id":"3308120","regency_id":"3308","name":"TEMPURAN"},{"id":"3308130","regency_id":"3308","name":"KAJORAN"},{"id":"3308140","regency_id":"3308","name":"KALIANGKRIK"},{"id":"3308150","regency_id":"3308","name":"BANDONGAN"},{"id":"3308160","regency_id":"3308","name":"WINDUSARI"},{"id":"3308170","regency_id":"3308","name":"SECANG"},{"id":"3308180","regency_id":"3308","name":"TEGALREJO"},{"id":"3308190","regency_id":"3308","name":"PAKIS"},{"id":"3308200","regency_id":"3308","name":"GRABAG"},{"id":"3308210","regency_id":"3308","name":"NGABLAK"}]