[{"id":"1105110008","district_id":"1105110","name":"CEK MBON"},{"id":"1105110018","district_id":"1105110","name":"SEUNEUBOK PIDIE"},{"id":"1105110019","district_id":"1105110","name":"KUALA LEUGE"},{"id":"1105110020","district_id":"1105110","name":"SEUNEUBOK PEUSANGAN"},{"id":"1105110023","district_id":"1105110","name":"LEUBUK PEMPENG"},{"id":"1105110024","district_id":"1105110","name":"DAMA TUTONG"},{"id":"1105110025","district_id":"1105110","name":"BALE BUYA"},{"id":"1105110026","district_id":"1105110","name":"MATANG GLEUM"},{"id":"1105110027","district_id":"1105110","name":"ALUE NIBONG"},{"id":"1105110028","district_id":"1105110","name":"BUKET PALA"},{"id":"1105110029","district_id":"1105110","name":"BLANG SIMPO"},{"id":"1105110030","district_id":"1105110","name":"PAYA KALUT"},{"id":"1105110031","district_id":"1105110","name":"ALUE DUA PAYA GAJAH"},{"id":"1105110032","district_id":"1105110","name":"SEUNEUBOK ACEH"},{"id":"1105110033","district_id":"1105110","name":"UTEUN DAMA"},{"id":"1105110034","district_id":"1105110","name":"PAYA MEULIGO"},{"id":"1105110035","district_id":"1105110","name":"PUNTI"},{"id":"1105110036","district_id":"1105110","name":"KEUMUNENG"},{"id":"1105110037","district_id":"1105110","name":"BANGKA RIMUENG"},{"id":"1105110038","district_id":"1105110","name":"LEUGE"},{"id":"1105110039","district_id":"1105110","name":"LHOK DALAM"},{"id":"1105110040","district_id":"1105110","name":"BANDRONG"},{"id":"1105110042","district_id":"1105110","name":"TANAH RATA"},{"id":"1105110043","district_id":"1105110","name":"TUALANG"},{"id":"1105110044","district_id":"1105110","name":"KEUDE PEUREULAK"},{"id":"1105110045","district_id":"1105110","name":"COT MUDA ITAM"},{"id":"1105110046","district_id":"1105110","name":"PASIR PUTIH"},{"id":"1105110047","district_id":"1105110","name":"BLANG BETRA"},{"id":"1105110055","district_id":"1105110","name":"BEUSA MEURANOU"},{"id":"1105110056","district_id":"1105110","name":"SEUMATANG MUDA ITAM"},{"id":"1105110057","district_id":"1105110","name":"BLANG BALOK"},{"id":"1105110058","district_id":"1105110","name":"KUALA BUGAK"},{"id":"1105110059","district_id":"1105110","name":"PAYA LIPAH"},{"id":"1105110060","district_id":"1105110","name":"COT GEULUMPANG"},{"id":"1105110062","district_id":"1105110","name":"COT KEH"},{"id":"1105110063","district_id":"1105110","name":"BLANG BATEE"},{"id":"1105110064","district_id":"1105110","name":"ALUE RAMBONG"},{"id":"1105110065","district_id":"1105110","name":"MATANG PEULAWI"}]