[{"id":"1212230001","district_id":"1212230","name":"TELAGA SARI"},{"id":"1212230002","district_id":"1212230","name":"SEI MENCIRIM"},{"id":"1212230003","district_id":"1212230","name":"SUKA MAJU"},{"id":"1212230004","district_id":"1212230","name":"SEI BERAS SEKATA"},{"id":"1212230005","district_id":"1212230","name":"TANJUNG SELAMAT"},{"id":"1212230006","district_id":"1212230","name":"SUNGGAL KANAN"},{"id":"1212230007","district_id":"1212230","name":"MEDAN KRIO"},{"id":"1212230008","district_id":"1212230","name":"PAYA GELI"},{"id":"1212230009","district_id":"1212230","name":"PUJI MULYO"},{"id":"1212230010","district_id":"1212230","name":"SEI SEMAYANG"},{"id":"1212230011","district_id":"1212230","name":"SUMBER MELATI DISKI"},{"id":"1212230012","district_id":"1212230","name":"SERBA JADI"},{"id":"1212230013","district_id":"1212230","name":"MULYOREJO"},{"id":"1212230014","district_id":"1212230","name":"KAMPUNG LALANG"},{"id":"1212230015","district_id":"1212230","name":"PURWODADI"},{"id":"1212230016","district_id":"1212230","name":"TANJUNG GUSTA"},{"id":"1212230017","district_id":"1212230","name":"HELVETIA"}]