[{"id":"1221050001","district_id":"1221050","name":"BATU GAJAH"},{"id":"1221050002","district_id":"1221050","name":"HAPUNG"},{"id":"1221050003","district_id":"1221050","name":"HAPUNG TOROP"},{"id":"1221050004","district_id":"1221050","name":"BONAN DOLOK"},{"id":"1221050038","district_id":"1221050","name":"MANDIAN"},{"id":"1221050039","district_id":"1221050","name":"PARAPAT"},{"id":"1221050040","district_id":"1221050","name":"HANDIO"},{"id":"1221050041","district_id":"1221050","name":"HORUAN"},{"id":"1221050042","district_id":"1221050","name":"HARANG JAE"},{"id":"1221050043","district_id":"1221050","name":"HARANG JULU"},{"id":"1221050044","district_id":"1221050","name":"GUNUNG TUA"},{"id":"1221050045","district_id":"1221050","name":"PASIR JULU"},{"id":"1221050046","district_id":"1221050","name":"LUMBAN HUAYAN"},{"id":"1221050047","district_id":"1221050","name":"SIBORNA (SIBORIS BUNUT)"},{"id":"1221050048","district_id":"1221050","name":"MANANTI SOSA JULU"},{"id":"1221050049","district_id":"1221050","name":"HUTA IMBARU"},{"id":"1221050050","district_id":"1221050","name":"SISOMA"},{"id":"1221050051","district_id":"1221050","name":"MONDANG"},{"id":"1221050052","district_id":"1221050","name":"SIMARANCAR"},{"id":"1221050053","district_id":"1221050","name":"HUTA RAJA LAMA"},{"id":"1221050057","district_id":"1221050","name":"TJ BOTUNG SOSA JAE"},{"id":"1221050079","district_id":"1221050","name":"AEK TINGA"},{"id":"1221050080","district_id":"1221050","name":"GUNUNG BARINGIN"},{"id":"1221050082","district_id":"1221050","name":"PASAR UJUNG BATU"},{"id":"1221050083","district_id":"1221050","name":"UJUNG BATU"},{"id":"1221050084","district_id":"1221050","name":"JANJI RAJA"},{"id":"1221050085","district_id":"1221050","name":"RAO RAO DOLOK"},{"id":"1221050086","district_id":"1221050","name":"PARAU SORAT"},{"id":"1221050087","district_id":"1221050","name":"AER BALE"},{"id":"1221050088","district_id":"1221050","name":"TANJUNG BALE"},{"id":"1221050089","district_id":"1221050","name":"AMPOLU"},{"id":"1221050090","district_id":"1221050","name":"SIGINDUANG"},{"id":"1221050091","district_id":"1221050","name":"RAMBA"},{"id":"1221050092","district_id":"1221050","name":"ROBURAN"},{"id":"1221050093","district_id":"1221050","name":"TANJUNG"},{"id":"1221050094","district_id":"1221050","name":"HURUNG JILOK"},{"id":"1221050095","district_id":"1221050","name":"PASIR JAE"},{"id":"1221050096","district_id":"1221050","name":"SUNGAI JIOR"},{"id":"1221050097","district_id":"1221050","name":"PIR SOSA PLASMA MOND"}]