[{"id":"1501082001","district_id":"1501082","name":"MUKAI HILIR"},{"id":"1501082002","district_id":"1501082","name":"SUNGAI LANGKAP"},{"id":"1501082003","district_id":"1501082","name":"SUNGAI KUNING"},{"id":"1501082004","district_id":"1501082","name":"PASIR JAYA"},{"id":"1501082005","district_id":"1501082","name":"MUKAI PINTU"},{"id":"1501082006","district_id":"1501082","name":"MUKAI TENGAH"},{"id":"1501082007","district_id":"1501082","name":"MUKAI MUDIK"},{"id":"1501082008","district_id":"1501082","name":"TEBING TINGGI"},{"id":"1501082009","district_id":"1501082","name":"SENIMPIK"},{"id":"1501082010","district_id":"1501082","name":"MUKAI TINGGI"},{"id":"1501082011","district_id":"1501082","name":"LUBUK TABUN"},{"id":"1501082012","district_id":"1501082","name":"MUKAI SEBERANG"},{"id":"1501082013","district_id":"1501082","name":"TALANG TINGGI"},{"id":"1501082014","district_id":"1501082","name":"KOTO LUA"}]