[{"id":"1706010016","district_id":"1706010","name":"AIR BULUH"},{"id":"1706010017","district_id":"1706010","name":"PULAU BARU"},{"id":"1706010018","district_id":"1706010","name":"SEMUNDAM"},{"id":"1706010019","district_id":"1706010","name":"TANJUNG JAYA"},{"id":"1706010020","district_id":"1706010","name":"DUSUN SIBAK"},{"id":"1706010021","district_id":"1706010","name":"MEDAN JAYA"},{"id":"1706010022","district_id":"1706010","name":"TANJUNG HARAPAN"},{"id":"1706010023","district_id":"1706010","name":"PASAR IPUH"},{"id":"1706010024","district_id":"1706010","name":"MANUNGGAL JAYA"},{"id":"1706010025","district_id":"1706010","name":"RETAK HILIR"},{"id":"1706010028","district_id":"1706010","name":"PULAI PAYUNG"},{"id":"1706010029","district_id":"1706010","name":"TANJUNG MEDAN"},{"id":"1706010030","district_id":"1706010","name":"TIRTA MULYA"},{"id":"1706010031","district_id":"1706010","name":"PASAR BARU"},{"id":"1706010032","district_id":"1706010","name":"PULAU MAKMUR"},{"id":"1706010033","district_id":"1706010","name":"MUNDAM MARAP"}]