[{"id":"1706032001","district_id":"1706032","name":"SUNGAI JERINJING"},{"id":"1706032002","district_id":"1706032","name":"PONDOK BARU"},{"id":"1706032003","district_id":"1706032","name":"SUNGAI IPUH"},{"id":"1706032004","district_id":"1706032","name":"SUNGAI GADING"},{"id":"1706032005","district_id":"1706032","name":"SURIAN BUNGKAL"},{"id":"1706032006","district_id":"1706032","name":"LUBUK SAHUNG"},{"id":"1706032007","district_id":"1706032","name":"LUBUK BANGKO"},{"id":"1706032008","district_id":"1706032","name":"TALANG BUAI"},{"id":"1706032009","district_id":"1706032","name":"AUR CINA"},{"id":"1706032010","district_id":"1706032","name":"SUNGAI IPUH SATU"},{"id":"1706032011","district_id":"1706032","name":"SUNGAI IPUH DUA"},{"id":"1706032012","district_id":"1706032","name":"TALANG MEDAN"}]