[{"id":"3204070001","district_id":"3204070","name":"NEGLASARI"},{"id":"3204070003","district_id":"3204070","name":"IBUN"},{"id":"3204070004","district_id":"3204070","name":"LAKSANA"},{"id":"3204070005","district_id":"3204070","name":"MEKARWANGI"},{"id":"3204070006","district_id":"3204070","name":"SUDI"},{"id":"3204070007","district_id":"3204070","name":"CIBEET"},{"id":"3204070008","district_id":"3204070","name":"PANGGUH"},{"id":"3204070009","district_id":"3204070","name":"KARYALAKSANA"},{"id":"3204070010","district_id":"3204070","name":"LAMPEGAN"},{"id":"3204070011","district_id":"3204070","name":"TALUN"},{"id":"3204070012","district_id":"3204070","name":"TANGGULUN"}]