[{"id":"3206020001","district_id":"3206020","name":"CIDADAP"},{"id":"3206020002","district_id":"3206020","name":"KUJANG"},{"id":"3206020003","district_id":"3206020","name":"SARIMUKTI"},{"id":"3206020004","district_id":"3206020","name":"CIAWI"},{"id":"3206020005","district_id":"3206020","name":"CIKAPINIS"},{"id":"3206020006","district_id":"3206020","name":"CIKUPA"},{"id":"3206020007","district_id":"3206020","name":"KARANGNUNGGAL"},{"id":"3206020008","district_id":"3206020","name":"KARANGMEKAR"},{"id":"3206020009","district_id":"3206020","name":"CIBATUIRENG"},{"id":"3206020010","district_id":"3206020","name":"CIBATU"},{"id":"3206020011","district_id":"3206020","name":"SUKAWANGUN"},{"id":"3206020012","district_id":"3206020","name":"CINTAWANGI"},{"id":"3206020013","district_id":"3206020","name":"CIKUKULU"},{"id":"3206020014","district_id":"3206020","name":"SARIMANGGU"}]