[{"id":"3211160001","district_id":"3211160","name":"CIMUJA"},{"id":"3211160011","district_id":"3211160","name":"CIBEUREUM WETAN"},{"id":"3211160012","district_id":"3211160","name":"CIBEUREUM KULON"},{"id":"3211160013","district_id":"3211160","name":"MANDALAHERANG"},{"id":"3211160014","district_id":"3211160","name":"CIMALAKA"},{"id":"3211160015","district_id":"3211160","name":"SERANG"},{"id":"3211160016","district_id":"3211160","name":"GALUDRA"},{"id":"3211160017","district_id":"3211160","name":"CIKOLE"},{"id":"3211160018","district_id":"3211160","name":"TRUNAMANGGALA"},{"id":"3211160019","district_id":"3211160","name":"NYALINDUNG"},{"id":"3211160020","district_id":"3211160","name":"NALUK"},{"id":"3211160021","district_id":"3211160","name":"CITIMUN"},{"id":"3211160022","district_id":"3211160","name":"LICIN"},{"id":"3211160023","district_id":"3211160","name":"PADASARI"}]