[{"id":"3211020001","district_id":"3211020","name":"MANGUNARGA"},{"id":"3211020002","district_id":"3211020","name":"SAWAHDADAP"},{"id":"3211020003","district_id":"3211020","name":"SUKADANA"},{"id":"3211020004","district_id":"3211020","name":"CIHANJUANG"},{"id":"3211020005","district_id":"3211020","name":"CIKAHURIPAN"},{"id":"3211020006","district_id":"3211020","name":"SINDANGGALIH"},{"id":"3211020007","district_id":"3211020","name":"SINDANGPAKUON"},{"id":"3211020008","district_id":"3211020","name":"CIMANGGUNG"},{"id":"3211020009","district_id":"3211020","name":"TEGALMANGGUNG"},{"id":"3211020010","district_id":"3211020","name":"SINDULANG"},{"id":"3211020011","district_id":"3211020","name":"PASIRNANJUNG"}]