[{"id":"3215071001","district_id":"3215071","name":"PAMEKARAN"},{"id":"3215071002","district_id":"3215071","name":"CICINDE SELATAN"},{"id":"3215071003","district_id":"3215071","name":"CICINDE UTARA"},{"id":"3215071004","district_id":"3215071","name":"JAYAMUKTI"},{"id":"3215071005","district_id":"3215071","name":"GEMPOLKOLOT"},{"id":"3215071006","district_id":"3215071","name":"GEMPOL"},{"id":"3215071007","district_id":"3215071","name":"GEMBONGAN"},{"id":"3215071008","district_id":"3215071","name":"MEKARASIH"},{"id":"3215071009","district_id":"3215071","name":"BANYUASIH"},{"id":"3215071010","district_id":"3215071","name":"TALUNJAYA"},{"id":"3215071011","district_id":"3215071","name":"TANJUNG"},{"id":"3215071012","district_id":"3215071","name":"KUTARAHARJA"}]