[{"id":"3316160001","district_id":"3316160","name":"PELEMSENGIR"},{"id":"3316160002","district_id":"3316160","name":"PRIGI"},{"id":"3316160003","district_id":"3316160","name":"SAMBENG"},{"id":"3316160004","district_id":"3316160","name":"TINAPAN"},{"id":"3316160006","district_id":"3316160","name":"SONOKULON"},{"id":"3316160008","district_id":"3316160","name":"KACANGAN"},{"id":"3316160009","district_id":"3316160","name":"BICAK"},{"id":"3316160010","district_id":"3316160","name":"SENDANG"},{"id":"3316160011","district_id":"3316160","name":"WUKIRSARI"},{"id":"3316160012","district_id":"3316160","name":"KARANGANYAR"},{"id":"3316160013","district_id":"3316160","name":"TODANAN"},{"id":"3316160014","district_id":"3316160","name":"KETILENG"},{"id":"3316160015","district_id":"3316160","name":"COKROWATI"},{"id":"3316160016","district_id":"3316160","name":"KAJENGAN"},{"id":"3316160017","district_id":"3316160","name":"GUNUNGAN"},{"id":"3316160018","district_id":"3316160","name":"DRINGO"},{"id":"3316160019","district_id":"3316160","name":"DALANGAN"},{"id":"3316160020","district_id":"3316160","name":"CANDI"},{"id":"3316160021","district_id":"3316160","name":"GONDORIYO"},{"id":"3316160022","district_id":"3316160","name":"KEMBANG"},{"id":"3316160023","district_id":"3316160","name":"BEDINGIN"},{"id":"3316160024","district_id":"3316160","name":"LEDOK"},{"id":"3316160025","district_id":"3316160","name":"KEDUNGBACIN"}]