[{"id":"3317130001","district_id":"3317130","name":"SANETAN"},{"id":"3317130002","district_id":"3317130","name":"RAKITAN"},{"id":"3317130003","district_id":"3317130","name":"BENDO"},{"id":"3317130004","district_id":"3317130","name":"LABUHAN KIDUL"},{"id":"3317130005","district_id":"3317130","name":"SENDANGMULYO"},{"id":"3317130006","district_id":"3317130","name":"BLIMBING"},{"id":"3317130007","district_id":"3317130","name":"MANGGAR"},{"id":"3317130008","district_id":"3317130","name":"JATISARI"},{"id":"3317130009","district_id":"3317130","name":"LANGGAR"},{"id":"3317130011","district_id":"3317130","name":"JURANGJERO"},{"id":"3317130012","district_id":"3317130","name":"LERAN"},{"id":"3317130013","district_id":"3317130","name":"TRAHAN"},{"id":"3317130014","district_id":"3317130","name":"PANGKALAN"}]