[{"id":"3326030001","district_id":"3326030","name":"TEMBELANG GUNUNG"},{"id":"3326030002","district_id":"3326030","name":"PAMUTUH"},{"id":"3326030003","district_id":"3326030","name":"DEPOK"},{"id":"3326030004","district_id":"3326030","name":"WONOSIDO"},{"id":"3326030005","district_id":"3326030","name":"TIMBANGSARI"},{"id":"3326030006","district_id":"3326030","name":"SIDOMULYO"},{"id":"3326030007","district_id":"3326030","name":"KUTOREMBET"},{"id":"3326030008","district_id":"3326030","name":"LEBAKBARANG"},{"id":"3326030009","district_id":"3326030","name":"KAPUNDUTAN"},{"id":"3326030010","district_id":"3326030","name":"BANTAR KULON"},{"id":"3326030011","district_id":"3326030","name":"MENDOLO"}]