[{"id":"3374020001","district_id":"3374020","name":"GUNUNGPATI"},{"id":"3374020002","district_id":"3374020","name":"PLALANGAN"},{"id":"3374020003","district_id":"3374020","name":"SUMUREJO"},{"id":"3374020004","district_id":"3374020","name":"PAKINTELAN"},{"id":"3374020005","district_id":"3374020","name":"MANGUNSARI"},{"id":"3374020006","district_id":"3374020","name":"PATEMON"},{"id":"3374020007","district_id":"3374020","name":"NGIJO"},{"id":"3374020008","district_id":"3374020","name":"NONGKOSAWIT"},{"id":"3374020009","district_id":"3374020","name":"CEPOKO"},{"id":"3374020010","district_id":"3374020","name":"JATIREJO"},{"id":"3374020011","district_id":"3374020","name":"KANDRI"},{"id":"3374020012","district_id":"3374020","name":"PUNGANGAN"},{"id":"3374020013","district_id":"3374020","name":"KALISEGORO"},{"id":"3374020014","district_id":"3374020","name":"SEKARAN"},{"id":"3374020015","district_id":"3374020","name":"SUKOREJO"},{"id":"3374020016","district_id":"3374020","name":"SADENG"}]