[{"id":"3515020001","district_id":"3515020","name":"PRAMBON"},{"id":"3515020002","district_id":"3515020","name":"KAJARTENGGULI"},{"id":"3515020003","district_id":"3515020","name":"GEDANGROWO"},{"id":"3515020004","district_id":"3515020","name":"WIROBITING"},{"id":"3515020005","district_id":"3515020","name":"SIMPANG"},{"id":"3515020006","district_id":"3515020","name":"BULANG"},{"id":"3515020007","district_id":"3515020","name":"GAMPANG"},{"id":"3515020008","district_id":"3515020","name":"JATIKALANG"},{"id":"3515020009","district_id":"3515020","name":"PEJANGKUNGAN"},{"id":"3515020010","district_id":"3515020","name":"KEDUNGSUGO"},{"id":"3515020011","district_id":"3515020","name":"KEDUNGWONOKERTO"},{"id":"3515020012","district_id":"3515020","name":"BENDOTRETEK"},{"id":"3515020013","district_id":"3515020","name":"WONO PLINTAHAN"},{"id":"3515020014","district_id":"3515020","name":"KEDUNGKEMBAR"},{"id":"3515020015","district_id":"3515020","name":"JATI ALUN ALUN"},{"id":"3515020016","district_id":"3515020","name":"JEDONGCANGKRING"},{"id":"3515020017","district_id":"3515020","name":"CANGKRINGTURI"},{"id":"3515020018","district_id":"3515020","name":"SIMOGIRANG"},{"id":"3515020020","district_id":"3515020","name":"WATUTULIS"}]