[{"id":"3516020001","district_id":"3516020","name":"NGEMBAT"},{"id":"3516020002","district_id":"3516020","name":"JATIDUKUH"},{"id":"3516020003","district_id":"3516020","name":"KALIKATIR"},{"id":"3516020004","district_id":"3516020","name":"DILEM"},{"id":"3516020005","district_id":"3516020","name":"BEGAGANLIMO"},{"id":"3516020007","district_id":"3516020","name":"KEMASANTANI"},{"id":"3516020008","district_id":"3516020","name":"PADI"},{"id":"3516020009","district_id":"3516020","name":"CENTONG"},{"id":"3516020010","district_id":"3516020","name":"BAKALAN"},{"id":"3516020011","district_id":"3516020","name":"GONDANG"},{"id":"3516020012","district_id":"3516020","name":"PUGERAN"},{"id":"3516020013","district_id":"3516020","name":"KEBONTUNGGUL"},{"id":"3516020014","district_id":"3516020","name":"WONOPLOSO"},{"id":"3516020015","district_id":"3516020","name":"POHJEJER"},{"id":"3516020016","district_id":"3516020","name":"BENING"},{"id":"3516020017","district_id":"3516020","name":"KARANGKUTEN"},{"id":"3516020018","district_id":"3516020","name":"TAWAR"}]