[{"id":"3526130001","district_id":"3526130","name":"PANDAN LANJANG"},{"id":"3526130002","district_id":"3526130","name":"BATONAONG"},{"id":"3526130003","district_id":"3526130","name":"GLAGGA"},{"id":"3526130004","district_id":"3526130","name":"OMBUL"},{"id":"3526130005","district_id":"3526130","name":"BALUNG"},{"id":"3526130006","district_id":"3526130","name":"LAJING"},{"id":"3526130008","district_id":"3526130","name":"AROSBAYA"},{"id":"3526130009","district_id":"3526130","name":"KARANG DUWAK"},{"id":"3526130011","district_id":"3526130","name":"MANGKON"},{"id":"3526130013","district_id":"3526130","name":"CENDAGAH"},{"id":"3526130014","district_id":"3526130","name":"KARANG PAO"},{"id":"3526130015","district_id":"3526130","name":"MAKAM AGUNG"},{"id":"3526130016","district_id":"3526130","name":"PLAKARAN"},{"id":"3526130017","district_id":"3526130","name":"BUDURAN"},{"id":"3526130018","district_id":"3526130","name":"TAMBEGAN"}]