[{"id":"5307050001","district_id":"5307050","name":"TELUK KENARI"},{"id":"5307050002","district_id":"5307050","name":"KALABAHI BARAT"},{"id":"5307050003","district_id":"5307050","name":"ADANG BUOM"},{"id":"5307050004","district_id":"5307050","name":"BINONGKO"},{"id":"5307050005","district_id":"5307050","name":"MOTONGBANG"},{"id":"5307050006","district_id":"5307050","name":"KALABAHI KOTA"},{"id":"5307050007","district_id":"5307050","name":"WETABUA"},{"id":"5307050008","district_id":"5307050","name":"NUSA KENARI"},{"id":"5307050009","district_id":"5307050","name":"LENDOLA"},{"id":"5307050010","district_id":"5307050","name":"AIR KENARI"},{"id":"5307050011","district_id":"5307050","name":"KALABAHI TENGAH"},{"id":"5307050012","district_id":"5307050","name":"KALABAHI TIMUR"},{"id":"5307050013","district_id":"5307050","name":"MUTIARA"},{"id":"5307050017","district_id":"5307050","name":"WELAI TIMUR"},{"id":"5307050020","district_id":"5307050","name":"WELAI BARAT"},{"id":"5307050021","district_id":"5307050","name":"FANATING"}]