[{"id":"6203020001","district_id":"6203020","name":"BATANJUNG"},{"id":"6203020002","district_id":"6203020","name":"CEMARA LABAT"},{"id":"6203020003","district_id":"6203020","name":"PALAMPAI"},{"id":"6203020004","district_id":"6203020","name":"SUNGAI TERAS"},{"id":"6203020005","district_id":"6203020","name":"LUPAK DALAM"},{"id":"6203020006","district_id":"6203020","name":"TAMBAN BARU SELATAN"},{"id":"6203020011","district_id":"6203020","name":"TAMBAN LUPAK"},{"id":"6203020012","district_id":"6203020","name":"SIMPANG BUNGA TANJUNG"},{"id":"6203020013","district_id":"6203020","name":"BARANGGAU"},{"id":"6203020014","district_id":"6203020","name":"LUPAK TIMUR"},{"id":"6203020015","district_id":"6203020","name":"PEMATANG"},{"id":"6203020016","district_id":"6203020","name":"WARGO MULYO"},{"id":"6203020017","district_id":"6203020","name":"SEI BAKUT"}]