[{"id":"6306040002","district_id":"6306040","name":"TELAGA SILI SILI"},{"id":"6306040004","district_id":"6306040","name":"TANIRAN SELATAN"},{"id":"6306040008","district_id":"6306040","name":"TANIRAN KUBAH"},{"id":"6306040009","district_id":"6306040","name":"BAKARUNG"},{"id":"6306040011","district_id":"6306040","name":"ANGKINANG SELATAN"},{"id":"6306040014","district_id":"6306040","name":"TAWIA"},{"id":"6306040016","district_id":"6306040","name":"KAYU ABANG"},{"id":"6306040018","district_id":"6306040","name":"ANGKINANG"},{"id":"6306040020","district_id":"6306040","name":"BAMBAN SELATAN"},{"id":"6306040022","district_id":"6306040","name":"BAMBAN"},{"id":"6306040023","district_id":"6306040","name":"BAMBAN UTARA"}]