[{"id":"7210130001","district_id":"7210130","name":"LEBANU"},{"id":"7210130002","district_id":"7210130","name":"BOMBA"},{"id":"7210130003","district_id":"7210130","name":"BEKA"},{"id":"7210130004","district_id":"7210130","name":"SIBEDI"},{"id":"7210130005","district_id":"7210130","name":"PADENDE"},{"id":"7210130006","district_id":"7210130","name":"BINANGGA"},{"id":"7210130008","district_id":"7210130","name":"TINGGEDE"},{"id":"7210130009","district_id":"7210130","name":"BALIASE"},{"id":"7210130010","district_id":"7210130","name":"BOYABALIASE"},{"id":"7210130011","district_id":"7210130","name":"TINGGEDE SELATAN"}]