[{"id":"7313020001","district_id":"7313020","name":"WIRINGPALENNAE"},{"id":"7313020002","district_id":"7313020","name":"SITAMPAE"},{"id":"7313020003","district_id":"7313020","name":"ATAKKAE"},{"id":"7313020004","district_id":"7313020","name":"MADDUKKELLENG"},{"id":"7313020005","district_id":"7313020","name":"SIENGKANG"},{"id":"7313020006","district_id":"7313020","name":"PADDUPPA"},{"id":"7313020007","district_id":"7313020","name":"PATTIROSOMPE"},{"id":"7313020008","district_id":"7313020","name":"CEMPALAGI"},{"id":"7313020009","district_id":"7313020","name":"BULUPABBULU"},{"id":"7313020010","district_id":"7313020","name":"LAPONGKODA"},{"id":"7313020011","district_id":"7313020","name":"TEDDAOPU"},{"id":"7313020012","district_id":"7313020","name":"SALOMENRALENG"},{"id":"7313020013","district_id":"7313020","name":"LAELO"},{"id":"7313020014","district_id":"7313020","name":"WATALLIPUE"},{"id":"7313020016","district_id":"7313020","name":"MATTIROTAPPARENG"}]