[{"id":"7405112001","district_id":"7405112","name":"LAMBANDIA"},{"id":"7405112003","district_id":"7405112","name":"TOMBEKUKU"},{"id":"7405112004","district_id":"7405112","name":"IWOI MENDORO"},{"id":"7405112005","district_id":"7405112","name":"EPEESI"},{"id":"7405112006","district_id":"7405112","name":"BASALA"},{"id":"7405112007","district_id":"7405112","name":"LIPU MASAGENA"},{"id":"7405112008","district_id":"7405112","name":"POLO-POLOLI"},{"id":"7405112010","district_id":"7405112","name":"TEPOROMBUA"}]