[{"id":"9401042001","district_id":"9401042","name":"SOA"},{"id":"9401042002","district_id":"9401042","name":"TAMBAT"},{"id":"9401042003","district_id":"9401042","name":"SUMBER HARAPAN"},{"id":"9401042004","district_id":"9401042","name":"YASA MULYA"},{"id":"9401042005","district_id":"9401042","name":"WANINGGAP SAY"},{"id":"9401042006","district_id":"9401042","name":"WANINGGAP MIRAF"},{"id":"9401042007","district_id":"9401042","name":"ISANOMBIAS"},{"id":"9401042008","district_id":"9401042","name":"YABA MARU"},{"id":"9401042009","district_id":"9401042","name":"AMUNKAI"},{"id":"9401042010","district_id":"9401042","name":"HIDUP BARU"},{"id":"9401042011","district_id":"9401042","name":"SERMAYAM INDAH"},{"id":"9401042012","district_id":"9401042","name":"NGGUTI BOB"},{"id":"9401042013","district_id":"9401042","name":"BERSEHATI"},{"id":"9401042014","district_id":"9401042","name":"KAMANGI"}]