[{"id":"9418127001","district_id":"9418127","name":"PEKALEME"},{"id":"9418127002","district_id":"9418127","name":"TALEME"},{"id":"9418127003","district_id":"9418127","name":"GIKO"},{"id":"9418127005","district_id":"9418127","name":"KOTORAMBUR"},{"id":"9418127006","district_id":"9418127","name":"MINAGAME"},{"id":"9418127007","district_id":"9418127","name":"KARU"},{"id":"9418127008","district_id":"9418127","name":"TABUH"},{"id":"9418127009","district_id":"9418127","name":"GWAK DUGUNIK"},{"id":"9418127011","district_id":"9418127","name":"AMBIRIK"}]