[{"id":"1371010","regency_id":"1371","name":"BUNGUS TELUK KABUNG"},{"id":"1371020","regency_id":"1371","name":"LUBUK KILANGAN"},{"id":"1371030","regency_id":"1371","name":"LUBUK BEGALUNG"},{"id":"1371040","regency_id":"1371","name":"PADANG SELATAN"},{"id":"1371050","regency_id":"1371","name":"PADANG TIMUR"},{"id":"1371060","regency_id":"1371","name":"PADANG BARAT"},{"id":"1371070","regency_id":"1371","name":"PADANG UTARA"},{"id":"1371080","regency_id":"1371","name":"NANGGALO"},{"id":"1371090","regency_id":"1371","name":"KURANJI"},{"id":"1371100","regency_id":"1371","name":"PAUH"},{"id":"1371110","regency_id":"1371","name":"KOTO TANGAH"}]