[{"id":"3307010","regency_id":"3307","name":"WADASLINTANG"},{"id":"3307020","regency_id":"3307","name":"KEPIL"},{"id":"3307030","regency_id":"3307","name":"SAPURAN"},{"id":"3307031","regency_id":"3307","name":"KALIBAWANG"},{"id":"3307040","regency_id":"3307","name":"KALIWIRO"},{"id":"3307050","regency_id":"3307","name":"LEKSONO"},{"id":"3307051","regency_id":"3307","name":"SUKOHARJO"},{"id":"3307060","regency_id":"3307","name":"SELOMERTO"},{"id":"3307070","regency_id":"3307","name":"KALIKAJAR"},{"id":"3307080","regency_id":"3307","name":"KERTEK"},{"id":"3307090","regency_id":"3307","name":"WONOSOBO"},{"id":"3307100","regency_id":"3307","name":"WATUMALANG"},{"id":"3307110","regency_id":"3307","name":"MOJOTENGAH"},{"id":"3307120","regency_id":"3307","name":"GARUNG"},{"id":"3307130","regency_id":"3307","name":"KEJAJAR"}]