[{"id":"3374010","regency_id":"3374","name":"MIJEN"},{"id":"3374020","regency_id":"3374","name":"GUNUNG PATI"},{"id":"3374030","regency_id":"3374","name":"BANYUMANIK"},{"id":"3374040","regency_id":"3374","name":"GAJAH MUNGKUR"},{"id":"3374050","regency_id":"3374","name":"SEMARANG SELATAN"},{"id":"3374060","regency_id":"3374","name":"CANDISARI"},{"id":"3374070","regency_id":"3374","name":"TEMBALANG"},{"id":"3374080","regency_id":"3374","name":"PEDURUNGAN"},{"id":"3374090","regency_id":"3374","name":"GENUK"},{"id":"3374100","regency_id":"3374","name":"GAYAMSARI"},{"id":"3374110","regency_id":"3374","name":"SEMARANG TIMUR"},{"id":"3374120","regency_id":"3374","name":"SEMARANG UTARA"},{"id":"3374130","regency_id":"3374","name":"SEMARANG TENGAH"},{"id":"3374140","regency_id":"3374","name":"SEMARANG BARAT"},{"id":"3374150","regency_id":"3374","name":"TUGU"},{"id":"3374160","regency_id":"3374","name":"NGALIYAN"}]