[{"id":"3524010","regency_id":"3524","name":"SUKORAME"},{"id":"3524020","regency_id":"3524","name":"BLULUK"},{"id":"3524030","regency_id":"3524","name":"NGIMBANG"},{"id":"3524040","regency_id":"3524","name":"SAMBENG"},{"id":"3524050","regency_id":"3524","name":"MANTUP"},{"id":"3524060","regency_id":"3524","name":"KEMBANGBAHU"},{"id":"3524070","regency_id":"3524","name":"SUGIO"},{"id":"3524080","regency_id":"3524","name":"KEDUNGPRING"},{"id":"3524090","regency_id":"3524","name":"MODO"},{"id":"3524100","regency_id":"3524","name":"BABAT"},{"id":"3524110","regency_id":"3524","name":"PUCUK"},{"id":"3524120","regency_id":"3524","name":"SUKODADI"},{"id":"3524130","regency_id":"3524","name":"LAMONGAN"},{"id":"3524140","regency_id":"3524","name":"TIKUNG"},{"id":"3524141","regency_id":"3524","name":"SARIREJO"},{"id":"3524150","regency_id":"3524","name":"DEKET"},{"id":"3524160","regency_id":"3524","name":"GLAGAH"},{"id":"3524170","regency_id":"3524","name":"KARANGBINANGUN"},{"id":"3524180","regency_id":"3524","name":"TURI"},{"id":"3524190","regency_id":"3524","name":"KALITENGAH"},{"id":"3524200","regency_id":"3524","name":"KARANG GENENG"},{"id":"3524210","regency_id":"3524","name":"SEKARAN"},{"id":"3524220","regency_id":"3524","name":"MADURAN"},{"id":"3524230","regency_id":"3524","name":"LAREN"},{"id":"3524240","regency_id":"3524","name":"SOLOKURO"},{"id":"3524250","regency_id":"3524","name":"PACIRAN"},{"id":"3524260","regency_id":"3524","name":"BRONDONG"}]